django_site_health
tests
